MANIFEST.in
README.txt
setup.cfg
setup.py
docs/HISTORY.txt
docs/glossary.rst
docs/index.rst
docs/installation.rst
docs/usage.rst
pydataportability/__init__.py
pydataportability.xrd.egg-info/PKG-INFO
pydataportability.xrd.egg-info/SOURCES.txt
pydataportability.xrd.egg-info/dependency_links.txt
pydataportability.xrd.egg-info/namespace_packages.txt
pydataportability.xrd.egg-info/not-zip-safe
pydataportability.xrd.egg-info/requires.txt
pydataportability.xrd.egg-info/top_level.txt
pydataportability/xrd/__init__.py
pydataportability/xrd/parser.py
pydataportability/xrd/tests/__init__.py
pydataportability/xrd/tests/conftest.py
pydataportability/xrd/tests/test_xrd.py