Metadata-Version: 1.0
Name: pydataportability.xrd
Version: 0.4
Summary: An XRD parser for pydataportability
Home-page: http://pydataportability.net
Author: Christian Scholz
Author-email: cs@comlounge.net
License: BSD
Keywords: pydataportability xrd resource openweb dataportability oasis discovery metadata
Platform: UNKNOWN
Classifier: Programming Language :: Python
Classifier: Topic :: Software Development :: Libraries :: Python Modules
